medipy/__init__.py
medipy/hamilton.py
medipy/lipponen.py
medipy-0.0.6.dist-info/LICENSE
medipy-0.0.6.dist-info/METADATA
medipy-0.0.6.dist-info/WHEEL
medipy-0.0.6.dist-info/top_level.txt
medipy-0.0.6.dist-info/RECORD
