Metadata-Version: 2.1
Name: medipy
Version: 0.0.6
Summary: Code Collection for Medical Data Processing and Analysis
Home-page: https://github.com/zabler/medipy
Author: Nicolas Zabler
Author-email: neutralecho22@icloud.com
Keywords: medical,signals,analysis,processing
Classifier: Intended Audience :: Science/Research
Classifier: Programming Language :: Python :: 3.8
Classifier: License :: OSI Approved :: MIT License
Classifier: Operating System :: OS Independent
Requires-Python: >=3.8
License-File: LICENSE
Requires-Dist: numpy (>=1.21.4)
Requires-Dist: scipy (>=1.7.3)
Requires-Dist: matplotlib (>=3.5.0)
